dash_react_components/__init__.py
dash_react_components/_imports_.py
dash_react_components/dash_react_components.min.js
dash_react_components/dash_react_components.min.js.map
dash_react_components/dash_tabulator.py
dash_react_components/metadata.json
dash_react_components/package-info.json
dash_react_components-0.2.3.dist-info/LICENSE
dash_react_components-0.2.3.dist-info/METADATA
dash_react_components-0.2.3.dist-info/WHEEL
dash_react_components-0.2.3.dist-info/top_level.txt
dash_react_components-0.2.3.dist-info/RECORD
