Metadata-Version: 2.1
Name: dash-react-components
Version: 0.2.3
Summary: Project Description
Home-page: UNKNOWN
Author: pankaj <pankaj.pundir369@gmail.com>
Author-email: UNKNOWN
License: MIT
Platform: UNKNOWN
Classifier: Framework :: Dash
